mickey/__init__.py
mickey/admin.py
mickey/apps.py
mickey/exceptions.py
mickey/files.py
mickey/media.py
mickey/middleware.py
mickey/models.py
mickey/permissions.py
mickey/serializers.py
mickey/tests.py
mickey/urls.py
mickey/utils.py
mickey/views.py
mickey/widgets.py
mickey/migrations/__init__.py
mickey-0.0.5.dist-info/LICENSE
mickey-0.0.5.dist-info/METADATA
mickey-0.0.5.dist-info/WHEEL
mickey-0.0.5.dist-info/top_level.txt
mickey-0.0.5.dist-info/RECORD
