Metadata-Version: 2.1
Name: mickey
Version: 0.0.5
Summary: A Django package to build complete blog site.
Home-page: https://github.com/farhapartex/mickey
Author: Md Nazmul Hasan
Author-email: hasan08sust@gmail.com
License: UNKNOWN
Platform: UNKNOWN
Classifier: Programming Language :: Python :: 3
Classifier: License :: OSI Approved :: MIT License
Classifier: Operating System :: OS Independent
Requires-Python: >=3.6
